libgen_seedtools/__init__.py
libgen_seedtools/cli.py
libgen_seedtools/routines.py
libgen_seedtools/schemas.py
libgen_seedtools/transmission.py
lgst-0.5.11.dist-info/METADATA
lgst-0.5.11.dist-info/WHEEL
lgst-0.5.11.dist-info/entry_points.txt
lgst-0.5.11.dist-info/top_level.txt
lgst-0.5.11.dist-info/RECORD
