Metadata-Version: 2.2
Name: lgst
Version: 0.5.11
Summary: Add your description here
Author-email: Brandon Davis <libgen-seedtools@subdavis.com>, zrthstr <zrth1k@gmail.com>
License: MIT License
Project-URL: Repository, https://github.com/zrthstr/libgen-seedtools
Requires-Python: >=3.8
Requires-Dist: click>=8.1.7
Requires-Dist: click-aliases>=1.0.5
Requires-Dist: humanfriendly>=10.0
Requires-Dist: pydantic>=2.10.4
Requires-Dist: pytz>=2024.2
Requires-Dist: requests>=2.32.3
Requires-Dist: torrentool>=1.2.0
Requires-Dist: transmission-rpc>=7.0.11
